fmc_rest_client/__init__.py
fmc_rest_client/core/__init__.py
fmc_rest_client/core/base_clients.py
fmc_rest_client/core/base_resources.py
fmc_rest_client/core/pluralize.py
fmc_rest_client/resources/__init__.py
fmc_rest_client/resources/access_policy.py
fmc_rest_client/resources/ftdnat_policy.py
fmc_rest_client/resources/objects.py
fmc_rest_client-0.5.3.dist-info/DESCRIPTION.rst
fmc_rest_client-0.5.3.dist-info/METADATA
fmc_rest_client-0.5.3.dist-info/RECORD
fmc_rest_client-0.5.3.dist-info/WHEEL
fmc_rest_client-0.5.3.dist-info/metadata.json
fmc_rest_client-0.5.3.dist-info/top_level.txt
