Metadata-Version: 2.0
Name: fmc-rest-client
Version: 0.5.3
Summary: FMC REST API Client
Home-page: https://github.com/macvjuhu/fmc_rest_client
Author: Vikas Sharma
Author-email: macvjuhu@yahoo.com
License: MIT
Keywords: firepower management rest-api
Platform: UNKNOWN
Classifier: Development Status :: 3 - Alpha
Classifier: License :: OSI Approved :: MIT License
Classifier: Programming Language :: Python :: 3 :: Only
Classifier: Topic :: Security
Classifier: Topic :: System :: Networking :: Firewalls
Requires-Python: >=3
Requires-Dist: requests
